labthings_picamera2/__init__.py
labthings_picamera2/recalibrate_utils.py
labthings_picamera2/thing.py
labthings_picamera2-0.0.2.dist-info/LICENSE
labthings_picamera2-0.0.2.dist-info/METADATA
labthings_picamera2-0.0.2.dist-info/WHEEL
labthings_picamera2-0.0.2.dist-info/top_level.txt
labthings_picamera2-0.0.2.dist-info/RECORD
