Metadata-Version: 2.2
Name: labthings-picamera2
Version: 0.0.2
Summary: Picamera2 support for LabThings-FastAPI
Author-email: Richard Bowman <richard.bowman@cantab.net>
Project-URL: Homepage, https://github.com/rwb27/labthings-picamera2
Project-URL: Bug Tracker, https://github.com/rwb27/labthings-picamera2/issues
Classifier: Programming Language :: Python :: 3
Classifier: License :: OSI Approved :: MIT License
Classifier: Operating System :: OS Independent
Requires-Python: >=3.9
License-File: LICENSE
Requires-Dist: picamera2~=0.3.12
Requires-Dist: labthings-fastapi>=0.0.7
Requires-Dist: numpy
Requires-Dist: scipy
Requires-Dist: pillow
Provides-Extra: dev
Requires-Dist: labthings-fastapi[dev,server]; extra == "dev"
